ps_beet_bolt/__init__.py
ps_beet_bolt/bolt_item.py
ps_beet_bolt/register.py
ps_beet_bolt/argon/decorators.bolt
ps_beet_bolt/bolt_item/decorators.bolt
ps_beet_bolt/tungsten/decorators.bolt
ps_beet_bolt-0.4.0.dist-info/LICENSE
ps_beet_bolt-0.4.0.dist-info/METADATA
ps_beet_bolt-0.4.0.dist-info/WHEEL
ps_beet_bolt-0.4.0.dist-info/top_level.txt
ps_beet_bolt-0.4.0.dist-info/RECORD
